bigcommerce_cli/__init__.py
bigcommerce_cli/commands.py
bigcommerce_cli/delete/__init__.py
bigcommerce_cli/delete/delete_commands.py
bigcommerce_cli/get/__init__.py
bigcommerce_cli/get/get_commands.py
bigcommerce_cli/post/__init__.py
bigcommerce_cli/post/post_commands.py
bigcommerce_cli/put/__init__.py
bigcommerce_cli/put/put_commands.py
bigcommerce_cli/settings/__init__.py
bigcommerce_cli/settings/settings_commands.py
bigcommerce_cli/utils/__init__.py
bigcommerce_cli/utils/bigcommerce/__init__.py
bigcommerce_cli/utils/bigcommerce/base_resource.py
bigcommerce_cli/utils/bigcommerce/base_subresource.py
bigcommerce_cli/utils/bigcommerce/bigcommerce_request.py
bigcommerce_cli/utils/bigcommerce/resources/__init__.py
bigcommerce_cli/utils/bigcommerce/resources/customers.py
bigcommerce_cli/utils/bigcommerce/resources/order_products.py
bigcommerce_cli/utils/bigcommerce/resources/orders.py
bigcommerce_cli/utils/bigcommerce/resources/product_variants.py
bigcommerce_cli/utils/bigcommerce/resources/products.py
bigcommerce_cli/utils/bigcommerce/resources/webhooks.py
bigcommerce_cli/utils/click_extensions.py
bigcommerce_cli/utils/pretty_tables.py
bigcommerce_cli/utils/utils.py
bigcommerce_cli-0.2.0.dist-info/entry_points.txt
bigcommerce_cli-0.2.0.dist-info/WHEEL
bigcommerce_cli-0.2.0.dist-info/METADATA
bigcommerce_cli-0.2.0.dist-info/RECORD
