Metadata-Version: 2.1
Name: bigcommerce-cli
Version: 0.2.0
Summary: bcli is BigCommerce store management on the command line.
Home-page: https://github.com/dhartle4/bcli
Keywords: bigcommerce,cli
Author: dhartle4
Author-email: dhartle4@uncc.edu
Requires-Python: >=3.9,<4.0
Classifier: Programming Language :: Python :: 3
Classifier: Programming Language :: Python :: 3.9
Classifier: Programming Language :: Python :: 3.10
Requires-Dist: click (>=8.1.3,<9.0.0)
Requires-Dist: prettytable (>=3.3.0,<4.0.0)
Requires-Dist: pygments (>=2.13.0,<3.0.0)
Requires-Dist: requests (>=2.27.1,<3.0.0)
Project-URL: Repository, https://github.com/dhartle4/bcli
